__init__.py
ant1/ant1Interface_env.sh
ant1/catch_all.py
ant1/decoder.py
ant1/demo.py
ant1/dst.py
ant1/query_handler.py
ant1/ranker.py
ant1/util.py
ant1Interface-0.0.36.dist-info/METADATA
ant1Interface-0.0.36.dist-info/RECORD
ant1Interface-0.0.36.dist-info/WHEEL
bot/interface/interface_pb2.py
bot/interface/model_context_pb2.py
bot/interface/slot_pb2.py
bot/interface/user_pb2.py
python/google/__init__.py
python/google/protobuf/__init__.py
python/google/protobuf/any_pb2.py
python/google/protobuf/api_pb2.py
python/google/protobuf/compiler/__init__.py
python/google/protobuf/compiler/plugin_pb2.py
python/google/protobuf/descriptor.py
python/google/protobuf/descriptor_database.py
python/google/protobuf/descriptor_pb2.py
python/google/protobuf/descriptor_pool.py
python/google/protobuf/duration_pb2.py
python/google/protobuf/empty_pb2.py
python/google/protobuf/field_mask_pb2.py
python/google/protobuf/internal/__init__.py
python/google/protobuf/internal/_parameterized.py
python/google/protobuf/internal/api_implementation.py
python/google/protobuf/internal/containers.py
python/google/protobuf/internal/decoder.py
python/google/protobuf/internal/encoder.py
python/google/protobuf/internal/enum_type_wrapper.py
python/google/protobuf/internal/extension_dict.py
python/google/protobuf/internal/import_test_package/__init__.py
python/google/protobuf/internal/message_listener.py
python/google/protobuf/internal/python_message.py
python/google/protobuf/internal/testing_refleaks.py
python/google/protobuf/internal/type_checkers.py
python/google/protobuf/internal/well_known_types.py
python/google/protobuf/internal/wire_format.py
python/google/protobuf/json_format.py
python/google/protobuf/message.py
python/google/protobuf/message_factory.py
python/google/protobuf/proto_builder.py
python/google/protobuf/pyext/__init__.py
python/google/protobuf/pyext/cpp_message.py
python/google/protobuf/reflection.py
python/google/protobuf/service.py
python/google/protobuf/service_reflection.py
python/google/protobuf/source_context_pb2.py
python/google/protobuf/struct_pb2.py
python/google/protobuf/symbol_database.py
