Metadata-Version: 2.1
Name: ant1Interface
Version: 0.0.36
Author: wangyongqing.wyq
Author-email: wangyongqing.wyq@antgroup.com
Home-page: https://code.alipay.com/ai-dls/antnlp/blob/master/adabrain/common/interface/ant1/README.md
License: Copyright 2022 Ant Group Co., Ltd.
